odoo8_addon_stock_change_qty_reason-8.0.1.0.0.99.dev11-py3.8-nspkg.pth
odoo_addons/stock_change_qty_reason/README.rst
odoo_addons/stock_change_qty_reason/__init__.py
odoo_addons/stock_change_qty_reason/__openerp__.py
odoo_addons/stock_change_qty_reason/i18n/ar.po
odoo_addons/stock_change_qty_reason/i18n/bs.po
odoo_addons/stock_change_qty_reason/i18n/ca.po
odoo_addons/stock_change_qty_reason/i18n/cs.po
odoo_addons/stock_change_qty_reason/i18n/de.po
odoo_addons/stock_change_qty_reason/i18n/en_GB.po
odoo_addons/stock_change_qty_reason/i18n/es.po
odoo_addons/stock_change_qty_reason/i18n/es_CR.po
odoo_addons/stock_change_qty_reason/i18n/es_EC.po
odoo_addons/stock_change_qty_reason/i18n/es_MX.po
odoo_addons/stock_change_qty_reason/i18n/es_VE.po
odoo_addons/stock_change_qty_reason/i18n/et.po
odoo_addons/stock_change_qty_reason/i18n/fi.po
odoo_addons/stock_change_qty_reason/i18n/fr.po
odoo_addons/stock_change_qty_reason/i18n/hr.po
odoo_addons/stock_change_qty_reason/i18n/hu.po
odoo_addons/stock_change_qty_reason/i18n/it.po
odoo_addons/stock_change_qty_reason/i18n/ja.po
odoo_addons/stock_change_qty_reason/i18n/lt.po
odoo_addons/stock_change_qty_reason/i18n/mk.po
odoo_addons/stock_change_qty_reason/i18n/mn.po
odoo_addons/stock_change_qty_reason/i18n/nb.po
odoo_addons/stock_change_qty_reason/i18n/nl.po
odoo_addons/stock_change_qty_reason/i18n/nl_BE.po
odoo_addons/stock_change_qty_reason/i18n/pl.po
odoo_addons/stock_change_qty_reason/i18n/pt.po
odoo_addons/stock_change_qty_reason/i18n/pt_BR.po
odoo_addons/stock_change_qty_reason/i18n/pt_PT.po
odoo_addons/stock_change_qty_reason/i18n/ro.po
odoo_addons/stock_change_qty_reason/i18n/ru.po
odoo_addons/stock_change_qty_reason/i18n/sl.po
odoo_addons/stock_change_qty_reason/i18n/sr@latin.po
odoo_addons/stock_change_qty_reason/i18n/stock_change_qty_reason.pot
odoo_addons/stock_change_qty_reason/i18n/sv.po
odoo_addons/stock_change_qty_reason/i18n/th.po
odoo_addons/stock_change_qty_reason/i18n/tr.po
odoo8_addon_stock_change_qty_reason-8.0.1.0.0.99.dev11.dist-info/METADATA
odoo8_addon_stock_change_qty_reason-8.0.1.0.0.99.dev11.dist-info/WHEEL
odoo8_addon_stock_change_qty_reason-8.0.1.0.0.99.dev11.dist-info/namespace_packages.txt
odoo8_addon_stock_change_qty_reason-8.0.1.0.0.99.dev11.dist-info/top_level.txt
odoo8_addon_stock_change_qty_reason-8.0.1.0.0.99.dev11.dist-info/RECORD
